{
	"credit": "Made with Blockbench",
	"texture_size": [64, 64],
	"textures": {
		"0": "./tewort",
		"particle": "./tewort"
	},
	"elements": [
		{
			"from": [7.25, 13, 8],
			"to": [8.75, 16, 11],
			"rotation": {"angle": -45, "axis": "x", "origin": [8.75, 13, 8]},
			"faces": {
				"north": {"uv": [2.75, 5.5, 3.125, 6.25], "texture": "#0"},
				"east": {"uv": [0, 4, 0.75, 4.75], "texture": "#0"},
				"south": {"uv": [1.5, 4, 1.875, 4.75], "texture": "#0"},
				"west": {"uv": [0.75, 4, 0, 4.75], "texture": "#0"},
				"up": {"uv": [4, 5.875, 3.25, 5.5], "rotation": 90, "texture": "#0"},
				"down": {"uv": [6.25, 3.75, 5.5, 4.125], "rotation": 270, "texture": "#0"}
			}
		},
		{
			"from": [7, 15.53554, 5.449],
			"to": [9, 17.03554, 8.57],
			"rotation": {"angle": -45, "axis": "x", "origin": [7, 16.53554, 7.82844]},
			"faces": {
				"north": {"uv": [4.25, 6, 4.75, 6.375], "texture": "#0"},
				"east": {"uv": [4, 5.5, 4.75, 5.875], "texture": "#0"},
				"south": {"uv": [3.75, 6, 4.25, 6.375], "texture": "#0"},
				"west": {"uv": [4.75, 5.5, 4, 5.875], "texture": "#0"},
				"up": {"uv": [3.25, 5, 2.5, 4.5], "rotation": 90, "texture": "#0"},
				"down": {"uv": [0.75, 4.75, 0, 5.25], "rotation": 270, "texture": "#0"}
			}
		},
		{
			"from": [7.005, 15.11701, 8.79406],
			"to": [9, 16.67701, 10.41706],
			"rotation": {"angle": 45, "axis": "x", "origin": [7, 16.194, 8.53563]},
			"faces": {
				"north": {"uv": [5.25, 6, 5.75, 6.375], "texture": "#0"},
				"east": {"uv": [5.5, 5, 5.875, 5.375], "texture": "#0"},
				"south": {"uv": [4.75, 6, 5.25, 6.375], "texture": "#0"},
				"west": {"uv": [5.875, 5, 5.5, 5.375], "texture": "#0"},
				"up": {"uv": [1.125, 5.25, 0.75, 4.75], "rotation": 90, "texture": "#0"},
				"down": {"uv": [5.5, 2, 5.125, 2.5], "rotation": 270, "texture": "#0"}
			}
		},
		{
			"from": [7.2525, 11.96, 9.64408],
			"to": [8.7475, 13.46, 12.89408],
			"rotation": {"angle": -22.5, "axis": "x", "origin": [8.7475, 0, 2.64408]},
			"faces": {
				"north": {"uv": [6.25, 5, 6.625, 5.375], "texture": "#0"},
				"east": {"uv": [4.75, 4.5, 5.625, 4.875], "texture": "#0"},
				"south": {"uv": [6.25, 4.5, 6.625, 4.875], "texture": "#0"},
				"west": {"uv": [2.5, 5, 3.375, 5.375], "texture": "#0"},
				"up": {"uv": [4.375, 5.375, 3.5, 5], "rotation": 90, "texture": "#0"},
				"down": {"uv": [5.375, 5, 4.5, 5.375], "rotation": 270, "texture": "#0"}
			}
		},
		{
			"from": [7.255, 12.6142, 3.96032],
			"to": [8.745, 15.1142, 5.46032],
			"rotation": {"angle": 0, "axis": "y", "origin": [8.745, 7.6142, 17.46032]},
			"faces": {
				"north": {"uv": [1.5, 5.75, 1.875, 6.375], "texture": "#0"},
				"east": {"uv": [0.5, 5.75, 0.875, 6.375], "texture": "#0"},
				"south": {"uv": [1, 5.75, 1.375, 6.375], "texture": "#0"},
				"west": {"uv": [5.75, 1, 6.125, 1.625], "texture": "#0"},
				"up": {"uv": [6.625, 5.875, 6.25, 5.5], "rotation": 90, "texture": "#0"},
				"down": {"uv": [6.625, 6, 6.25, 6.375], "rotation": 270, "texture": "#0"}
			}
		},
		{
			"from": [7.2525, 17.62987, 5.066],
			"to": [8.7475, 18.20387, 6.4518],
			"rotation": {"angle": -22.5, "axis": "x", "origin": [8.7475, 12.62987, 18.56377]},
			"faces": {
				"north": {"uv": [7.25, 0.75, 7.625, 0.875], "texture": "#0"},
				"east": {"uv": [7.25, 0.25, 7.625, 0.375], "texture": "#0"},
				"south": {"uv": [0.5, 7.25, 0.875, 7.375], "texture": "#0"},
				"west": {"uv": [7.25, 0.5, 7.625, 0.625], "texture": "#0"},
				"up": {"uv": [0.875, 6.875, 0.5, 6.5], "rotation": 90, "texture": "#0"},
				"down": {"uv": [1.375, 6.5, 1, 6.875], "rotation": 270, "texture": "#0"}
			}
		},
		{
			"from": [7.99975, 12.6142, 1.4603],
			"to": [8.00025, 15.1142, 3.9603],
			"rotation": {"angle": 0, "axis": "y", "origin": [8.00025, -0.3858, 5.96032]},
			"faces": {
				"north": {"uv": [0, 0, 0, 0], "texture": "#0"},
				"east": {"uv": [4.625, 2.75, 4, 3.375], "texture": "#0"},
				"south": {"uv": [0, 0, 0, 0], "texture": "#0"},
				"west": {"uv": [4, 2.75, 4.625, 3.375], "texture": "#0"},
				"up": {"uv": [0, 0, 0, 0], "rotation": 90, "texture": "#0"},
				"down": {"uv": [0, 0, 0, 0], "rotation": 270, "texture": "#0"}
			}
		},
		{
			"from": [7.99975, 13.49806, 9.83542],
			"to": [8.00025, 15.49806, 12.58542],
			"rotation": {"angle": -22.5, "axis": "x", "origin": [8.00025, -0.46194, 2.83542]},
			"faces": {
				"north": {"uv": [0, 0, 0, 0], "texture": "#0"},
				"east": {"uv": [5.5, 3, 4.75, 3.5], "texture": "#0"},
				"south": {"uv": [0, 0, 0, 0], "texture": "#0"},
				"west": {"uv": [4.75, 3, 5.5, 3.5], "texture": "#0"},
				"up": {"uv": [0, 0, 0, 0], "rotation": 90, "texture": "#0"},
				"down": {"uv": [0, 0, 0, 0], "rotation": 270, "texture": "#0"}
			}
		},
		{
			"from": [7.2525, 11.96, 3.10592],
			"to": [8.7475, 13.46, 6.35592],
			"rotation": {"angle": 22.5, "axis": "x", "origin": [8.7475, 0, 13.35592]},
			"faces": {
				"north": {"uv": [2, 6.5, 2.375, 6.875], "texture": "#0"},
				"east": {"uv": [0, 5.25, 0.875, 5.625], "texture": "#0"},
				"south": {"uv": [1.5, 6.5, 1.875, 6.875], "texture": "#0"},
				"west": {"uv": [5.25, 0, 6.125, 0.375], "texture": "#0"},
				"up": {"uv": [6.125, 0.875, 5.25, 0.5], "rotation": 90, "texture": "#0"},
				"down": {"uv": [1.875, 5.25, 1, 5.625], "rotation": 270, "texture": "#0"}
			}
		},
		{
			"from": [7.255, 12.6142, 10.53968],
			"to": [8.745, 15.1142, 12.03968],
			"rotation": {"angle": 0, "axis": "y", "origin": [8.745, 7.6142, -1.46032]},
			"faces": {
				"north": {"uv": [5.75, 4.25, 6.125, 4.875], "texture": "#0"},
				"east": {"uv": [5.75, 1.75, 6.125, 2.375], "texture": "#0"},
				"south": {"uv": [2, 5.75, 2.375, 6.375], "texture": "#0"},
				"west": {"uv": [5.75, 2.5, 6.125, 3.125], "texture": "#0"},
				"up": {"uv": [3.625, 6.875, 3.25, 6.5], "rotation": 90, "texture": "#0"},
				"down": {"uv": [4.125, 6.5, 3.75, 6.875], "rotation": 270, "texture": "#0"}
			}
		},
		{
			"from": [7.2525, 17.62987, 9.5482],
			"to": [8.7475, 18.20387, 10.934],
			"rotation": {"angle": 22.5, "axis": "x", "origin": [8.7475, 12.62987, -2.56377]},
			"faces": {
				"north": {"uv": [1.5, 7.25, 1.875, 7.375], "texture": "#0"},
				"east": {"uv": [1, 7.25, 1.375, 7.375], "texture": "#0"},
				"south": {"uv": [7.25, 1, 7.625, 1.125], "texture": "#0"},
				"west": {"uv": [7.25, 1.25, 7.625, 1.375], "texture": "#0"},
				"up": {"uv": [4.625, 6.875, 4.25, 6.5], "rotation": 90, "texture": "#0"},
				"down": {"uv": [5.125, 6.5, 4.75, 6.875], "rotation": 270, "texture": "#0"}
			}
		},
		{
			"from": [7.99975, 12.6142, 12.0397],
			"to": [8.00025, 15.1142, 14.5397],
			"rotation": {"angle": 0, "axis": "y", "origin": [8.00025, -0.3858, 10.03968]},
			"faces": {
				"north": {"uv": [0, 0, 0, 0], "texture": "#0"},
				"east": {"uv": [4.625, 4.25, 4, 4.875], "texture": "#0"},
				"south": {"uv": [0, 0, 0, 0], "texture": "#0"},
				"west": {"uv": [4, 4.25, 4.625, 4.875], "texture": "#0"},
				"up": {"uv": [0, 0, 0, 0], "rotation": 90, "texture": "#0"},
				"down": {"uv": [0, 0, 0, 0], "rotation": 270, "texture": "#0"}
			}
		},
		{
			"from": [7.755, 16.5, 7.625],
			"to": [8.245, 26.75, 8.375],
			"rotation": {"angle": 0, "axis": "y", "origin": [8.248, 0, 7.625]},
			"faces": {
				"north": {"uv": [2.5, 5.375, 2.625, 8.625], "texture": "#0"},
				"east": {"uv": [2, 2.375, 2.25, 5.625], "texture": "#0"},
				"south": {"uv": [6.625, 1, 6.75, 4.25], "texture": "#0"},
				"west": {"uv": [2.25, 2.375, 2.5, 5.625], "texture": "#0"},
				"up": {"uv": [3.5, 4.625, 3.25, 4.5], "rotation": 90, "texture": "#0"},
				"down": {"uv": [3.5, 4.75, 3.25, 4.875], "rotation": 270, "texture": "#0"}
			}
		},
		{
			"from": [7.7525, 18.47, 7.125],
			"to": [8.2475, 19.259, 8.875],
			"rotation": {"angle": 0, "axis": "y", "origin": [8.2475, 0, 7.125]},
			"faces": {
				"north": {"uv": [5.25, 1.25, 5.375, 1.5], "texture": "#0"},
				"east": {"uv": [6.75, 1.5, 7.25, 1.75], "texture": "#0"},
				"south": {"uv": [5.25, 1, 5.375, 1.25], "texture": "#0"},
				"west": {"uv": [6.75, 1.75, 7.25, 2], "texture": "#0"},
				"up": {"uv": [1.5, 7.125, 1, 7], "rotation": 90, "texture": "#0"},
				"down": {"uv": [2, 7, 1.5, 7.125], "rotation": 270, "texture": "#0"}
			}
		},
		{
			"from": [7.7525, 19.654, 7.125],
			"to": [8.2475, 20.443, 8.875],
			"rotation": {"angle": 0, "axis": "y", "origin": [8.2475, 0, 7.125]},
			"faces": {
				"north": {"uv": [5.25, 1.75, 5.375, 2], "texture": "#0"},
				"east": {"uv": [6.75, 2, 7.25, 2.25], "texture": "#0"},
				"south": {"uv": [5.25, 1.5, 5.375, 1.75], "texture": "#0"},
				"west": {"uv": [6.75, 2.25, 7.25, 2.5], "texture": "#0"},
				"up": {"uv": [2.5, 7.125, 2, 7], "rotation": 90, "texture": "#0"},
				"down": {"uv": [3.25, 7, 2.75, 7.125], "rotation": 270, "texture": "#0"}
			}
		},
		{
			"from": [7.7525, 20.836, 7.125],
			"to": [8.2475, 21.625, 8.875],
			"rotation": {"angle": 0, "axis": "y", "origin": [8.2475, 0, 7.125]},
			"faces": {
				"north": {"uv": [7.25, 1.5, 7.375, 1.75], "texture": "#0"},
				"east": {"uv": [6.75, 2.5, 7.25, 2.75], "texture": "#0"},
				"south": {"uv": [5.5, 4.25, 5.625, 4.5], "texture": "#0"},
				"west": {"uv": [2.75, 6.75, 3.25, 7], "texture": "#0"},
				"up": {"uv": [3.75, 7.125, 3.25, 7], "rotation": 90, "texture": "#0"},
				"down": {"uv": [4.25, 7, 3.75, 7.125], "rotation": 270, "texture": "#0"}
			}
		},
		{
			"from": [7.7525, 22.017, 7.125],
			"to": [8.2475, 22.806, 8.875],
			"rotation": {"angle": 0, "axis": "y", "origin": [8.2475, 0, 7.125]},
			"faces": {
				"north": {"uv": [2, 7.25, 2.125, 7.5], "texture": "#0"},
				"east": {"uv": [6.75, 2.75, 7.25, 3], "texture": "#0"},
				"south": {"uv": [7.25, 1.75, 7.375, 2], "texture": "#0"},
				"west": {"uv": [6.75, 3, 7.25, 3.25], "texture": "#0"},
				"up": {"uv": [4.75, 7.125, 4.25, 7], "rotation": 90, "texture": "#0"},
				"down": {"uv": [5.25, 7, 4.75, 7.125], "rotation": 270, "texture": "#0"}
			}
		},
		{
			"from": [7.7525, 23.2, 7.125],
			"to": [8.2475, 23.989, 8.875],
			"rotation": {"angle": 0, "axis": "y", "origin": [8.2475, 0, 7.125]},
			"faces": {
				"north": {"uv": [2.25, 7.25, 2.375, 7.5], "texture": "#0"},
				"east": {"uv": [6.75, 3.25, 7.25, 3.5], "texture": "#0"},
				"south": {"uv": [7.25, 2, 7.375, 2.25], "texture": "#0"},
				"west": {"uv": [6.75, 3.5, 7.25, 3.75], "texture": "#0"},
				"up": {"uv": [5.75, 7.125, 5.25, 7], "rotation": 90, "texture": "#0"},
				"down": {"uv": [6.25, 7, 5.75, 7.125], "rotation": 270, "texture": "#0"}
			}
		},
		{
			"from": [7.7525, 24.385, 7.125],
			"to": [8.2475, 25.174, 8.875],
			"rotation": {"angle": 0, "axis": "y", "origin": [8.2475, 0, 7.125]},
			"faces": {
				"north": {"uv": [7.25, 2.5, 7.375, 2.75], "texture": "#0"},
				"east": {"uv": [6.75, 3.75, 7.25, 4], "texture": "#0"},
				"south": {"uv": [7.25, 2.25, 7.375, 2.5], "texture": "#0"},
				"west": {"uv": [6.75, 4, 7.25, 4.25], "texture": "#0"},
				"up": {"uv": [6.75, 7.125, 6.25, 7], "rotation": 90, "texture": "#0"},
				"down": {"uv": [7.25, 7, 6.75, 7.125], "rotation": 270, "texture": "#0"}
			}
		},
		{
			"from": [7.7525, 25.565, 7.125],
			"to": [8.2475, 26.354, 8.875],
			"rotation": {"angle": 0, "axis": "y", "origin": [8.2475, 0, 7.125]},
			"faces": {
				"north": {"uv": [7.25, 2.75, 7.375, 3], "texture": "#0"},
				"east": {"uv": [6.75, 4.25, 7.25, 4.5], "texture": "#0"},
				"south": {"uv": [2.75, 7.25, 2.875, 7.5], "texture": "#0"},
				"west": {"uv": [6.75, 4.5, 7.25, 4.75], "texture": "#0"},
				"up": {"uv": [0.5, 7.375, 0, 7.25], "rotation": 90, "texture": "#0"},
				"down": {"uv": [7.75, 0, 7.25, 0.125], "rotation": 270, "texture": "#0"}
			}
		},
		{
			"from": [7.9995, 16, 4],
			"to": [8.0005, 32, 12],
			"rotation": {"angle": 0, "axis": "y", "origin": [8.0005, 0, 4]},
			"faces": {
				"north": {"uv": [0, 0, 0, 0], "texture": "#0"},
				"east": {"uv": [2, 0, 0, 4], "texture": "#0"},
				"south": {"uv": [0, 0, 0, 0], "texture": "#0"},
				"west": {"uv": [0, 0, 2, 4], "texture": "#0"},
				"up": {"uv": [0, 0, 0, 0], "rotation": 90, "texture": "#0"},
				"down": {"uv": [0, 0, 0, 0], "rotation": 270, "texture": "#0"}
			}
		},
		{
			"from": [7.99975, 13.49806, 3.41458],
			"to": [8.00025, 15.49806, 6.16458],
			"rotation": {"angle": 22.5, "axis": "x", "origin": [8.00025, -0.46194, 13.16458]},
			"faces": {
				"north": {"uv": [0, 0, 0, 0], "texture": "#0"},
				"east": {"uv": [5.5, 4, 4.75, 4.5], "texture": "#0"},
				"south": {"uv": [0, 0, 0, 0], "texture": "#0"},
				"west": {"uv": [4.75, 4, 5.5, 4.5], "texture": "#0"},
				"up": {"uv": [0, 0, 0, 0], "rotation": 90, "texture": "#0"},
				"down": {"uv": [0, 0, 0, 0], "rotation": 270, "texture": "#0"}
			}
		},
		{
			"from": [7.99975, 10.6142, 3.96032],
			"to": [8.00025, 12.6142, 5.46032],
			"rotation": {"angle": 0, "axis": "y", "origin": [8.00025, -0.3858, -0.03968]},
			"faces": {
				"north": {"uv": [0, 0, 0, 0], "texture": "#0"},
				"east": {"uv": [6.625, 1.5, 6.25, 2], "texture": "#0"},
				"south": {"uv": [0, 0, 0, 0], "texture": "#0"},
				"west": {"uv": [6.25, 1.5, 6.625, 2], "texture": "#0"},
				"up": {"uv": [0, 0, 0, 0], "rotation": 90, "texture": "#0"},
				"down": {"uv": [0, 0, 0, 0], "rotation": 270, "texture": "#0"}
			}
		},
		{
			"from": [7.99975, 10.6142, 10.53968],
			"to": [8.00025, 12.6142, 12.03968],
			"rotation": {"angle": 0, "axis": "y", "origin": [8.00025, -0.3858, 16.03968]},
			"faces": {
				"north": {"uv": [0, 0, 0, 0], "texture": "#0"},
				"east": {"uv": [6.625, 2.5, 6.25, 3], "texture": "#0"},
				"south": {"uv": [0, 0, 0, 0], "texture": "#0"},
				"west": {"uv": [6.25, 2.5, 6.625, 3], "texture": "#0"},
				"up": {"uv": [0, 0, 0, 0], "rotation": 90, "texture": "#0"},
				"down": {"uv": [0, 0, 0, 0], "rotation": 270, "texture": "#0"}
			}
		},
		{
			"from": [7.99975, 9, 6],
			"to": [8.00025, 13, 10],
			"rotation": {"angle": 0, "axis": "y", "origin": [8.00025, 0, 7]},
			"faces": {
				"north": {"uv": [0, 0, 0, 0], "texture": "#0"},
				"east": {"uv": [3, 0.875, 1.875, 2], "texture": "#0"},
				"south": {"uv": [0, 0, 0, 0], "texture": "#0"},
				"west": {"uv": [1.875, 0.875, 3, 2], "texture": "#0"},
				"up": {"uv": [0, 0, 0, 0], "rotation": 90, "texture": "#0"},
				"down": {"uv": [0, 0, 0, 0], "rotation": 270, "texture": "#0"}
			}
		},
		{
			"from": [7.25, 0, 7.25],
			"to": [8.75, 6, 8.75],
			"rotation": {"angle": 0, "axis": "y", "origin": [8.75, 0, 7.25]},
			"faces": {
				"north": {"uv": [3.5, 3.5, 3.875, 5], "texture": "#0"},
				"east": {"uv": [2.5, 3, 2.875, 4.5], "texture": "#0"},
				"south": {"uv": [3, 3, 3.375, 4.5], "texture": "#0"},
				"west": {"uv": [3.5, 2, 3.875, 3.5], "texture": "#0"},
				"up": {"uv": [3.125, 6.625, 2.75, 6.25], "rotation": 90, "texture": "#0"},
				"down": {"uv": [6.625, 3, 6.25, 3.375], "rotation": 270, "texture": "#0"}
			}
		},
		{
			"from": [7.25, 6, 5],
			"to": [8.75, 7.5, 11],
			"rotation": {"angle": 0, "axis": "y", "origin": [8.75, 0, 5]},
			"faces": {
				"north": {"uv": [6.25, 4, 6.625, 4.375], "texture": "#0"},
				"east": {"uv": [3.75, 0, 5.25, 0.375], "texture": "#0"},
				"south": {"uv": [6.25, 3.5, 6.625, 3.875], "texture": "#0"},
				"west": {"uv": [3.75, 0.5, 5.25, 0.875], "texture": "#0"},
				"up": {"uv": [5.25, 1.375, 3.75, 1], "rotation": 90, "texture": "#0"},
				"down": {"uv": [5.25, 1.5, 3.75, 1.875], "rotation": 270, "texture": "#0"}
			}
		},
		{
			"from": [7, 7.5, 7],
			"to": [9, 9, 9],
			"rotation": {"angle": 0, "axis": "y", "origin": [9, 0, 7]},
			"faces": {
				"north": {"uv": [6.25, 0.5, 6.75, 0.875], "texture": "#0"},
				"east": {"uv": [5.75, 6, 6.25, 6.375], "texture": "#0"},
				"south": {"uv": [0, 6.25, 0.5, 6.625], "texture": "#0"},
				"west": {"uv": [6.25, 0, 6.75, 0.375], "texture": "#0"},
				"up": {"uv": [2, 5.25, 1.5, 4.75], "rotation": 90, "texture": "#0"},
				"down": {"uv": [0.5, 5.75, 0, 6.25], "rotation": 270, "texture": "#0"}
			}
		},
		{
			"from": [7, 6.5, 7.25],
			"to": [9, 7.5, 8.75],
			"rotation": {"angle": 0, "axis": "y", "origin": [9, 0, 7.25]},
			"faces": {
				"north": {"uv": [6.75, 1.25, 7.25, 1.5], "texture": "#0"},
				"east": {"uv": [6.75, 4.75, 7.125, 5], "texture": "#0"},
				"south": {"uv": [6.75, 1, 7.25, 1.25], "texture": "#0"},
				"west": {"uv": [6.75, 5, 7.125, 5.25], "texture": "#0"},
				"up": {"uv": [6.125, 3.75, 5.75, 3.25], "rotation": 90, "texture": "#0"},
				"down": {"uv": [3.625, 6, 3.25, 6.5], "rotation": 270, "texture": "#0"}
			}
		},
		{
			"from": [7.99975, 5, 4],
			"to": [8.00025, 8.5, 7],
			"rotation": {"angle": 0, "axis": "y", "origin": [8.00025, 0, 7]},
			"faces": {
				"north": {"uv": [0, 0, 0, 0], "texture": "#0"},
				"east": {"uv": [3.5, 2, 2.75, 2.875], "texture": "#0"},
				"south": {"uv": [0, 0, 0, 0], "texture": "#0"},
				"west": {"uv": [2.75, 2, 3.5, 2.875], "texture": "#0"},
				"up": {"uv": [0, 0, 0, 0], "rotation": 90, "texture": "#0"},
				"down": {"uv": [0, 0, 0, 0], "rotation": 270, "texture": "#0"}
			}
		},
		{
			"from": [7.99975, 5, 9],
			"to": [8.00025, 8.5, 12],
			"rotation": {"angle": 0, "axis": "y", "origin": [8.00025, 0, 9]},
			"faces": {
				"north": {"uv": [0, 0, 0, 0], "texture": "#0"},
				"east": {"uv": [3.75, 1, 3, 1.875], "texture": "#0"},
				"south": {"uv": [0, 0, 0, 0], "texture": "#0"},
				"west": {"uv": [3, 1, 3.75, 1.875], "texture": "#0"},
				"up": {"uv": [0, 0, 0, 0], "rotation": 90, "texture": "#0"},
				"down": {"uv": [0, 0, 0, 0], "rotation": 270, "texture": "#0"}
			}
		},
		{
			"from": [7.375, 9, 7.375],
			"to": [8.625, 10.5, 8.625],
			"rotation": {"angle": 0, "axis": "y", "origin": [8.625, 0, 7.375]},
			"faces": {
				"north": {"uv": [0, 6.75, 0.375, 7.125], "texture": "#0"},
				"east": {"uv": [5.25, 6.5, 5.625, 6.875], "texture": "#0"},
				"south": {"uv": [5.75, 6.5, 6.125, 6.875], "texture": "#0"},
				"west": {"uv": [6.25, 6.5, 6.625, 6.875], "texture": "#0"},
				"up": {"uv": [7.125, 0.375, 6.75, 0], "rotation": 90, "texture": "#0"},
				"down": {"uv": [7.125, 0.5, 6.75, 0.875], "rotation": 270, "texture": "#0"}
			}
		},
		{
			"from": [7.25, 5, 5.5],
			"to": [7.2505, 6, 7],
			"rotation": {"angle": 0, "axis": "y", "origin": [7.2505, -5, 1]},
			"faces": {
				"north": {"uv": [0, 0, 0, 0.25], "texture": "#0"},
				"east": {"uv": [6.75, 6.25, 7.125, 6.5], "texture": "#0"},
				"south": {"uv": [0, 0, 0, 0.25], "texture": "#0"},
				"west": {"uv": [7.125, 6.25, 6.75, 6.5], "texture": "#0"},
				"up": {"uv": [0.375, 0, 0, 0], "rotation": 90, "texture": "#0"},
				"down": {"uv": [0.375, 0, 0, 0], "rotation": 270, "texture": "#0"}
			}
		},
		{
			"from": [8.7495, 5, 5.5],
			"to": [8.75, 6, 7],
			"rotation": {"angle": 0, "axis": "y", "origin": [8.7495, -5, 1]},
			"faces": {
				"north": {"uv": [0, 0, 0, 0.25], "texture": "#0"},
				"east": {"uv": [7.125, 6, 6.75, 6.25], "texture": "#0"},
				"south": {"uv": [0, 0, 0, 0.25], "texture": "#0"},
				"west": {"uv": [6.75, 6, 7.125, 6.25], "texture": "#0"},
				"up": {"uv": [0.375, 0, 0, 0], "rotation": 90, "texture": "#0"},
				"down": {"uv": [0.375, 0, 0, 0], "rotation": 270, "texture": "#0"}
			}
		},
		{
			"from": [8.7495, 5, 9],
			"to": [8.75, 6, 10.5],
			"rotation": {"angle": 0, "axis": "y", "origin": [8.7495, -5, 15]},
			"faces": {
				"north": {"uv": [0, 0, 0, 0.25], "texture": "#0"},
				"east": {"uv": [7.125, 5.5, 6.75, 5.75], "texture": "#0"},
				"south": {"uv": [0, 0, 0, 0.25], "texture": "#0"},
				"west": {"uv": [6.75, 5.5, 7.125, 5.75], "texture": "#0"},
				"up": {"uv": [0.375, 0, 0, 0], "rotation": 90, "texture": "#0"},
				"down": {"uv": [0.375, 0, 0, 0], "rotation": 270, "texture": "#0"}
			}
		},
		{
			"from": [7.25, 5, 9],
			"to": [7.2505, 6, 10.5],
			"rotation": {"angle": 0, "axis": "y", "origin": [7.2505, -5, 15]},
			"faces": {
				"north": {"uv": [0, 0, 0, 0.25], "texture": "#0"},
				"east": {"uv": [6.75, 6.75, 7.125, 7], "texture": "#0"},
				"south": {"uv": [0, 0, 0, 0.25], "texture": "#0"},
				"west": {"uv": [7.125, 6.75, 6.75, 7], "texture": "#0"},
				"up": {"uv": [0.375, 0, 0, 0], "rotation": 90, "texture": "#0"},
				"down": {"uv": [0.375, 0, 0, 0], "rotation": 270, "texture": "#0"}
			}
		},
		{
			"from": [7.7525, 17.285, 7.125],
			"to": [8.2475, 18.074, 8.875],
			"rotation": {"angle": 0, "axis": "y", "origin": [8.2475, 0, 7.125]},
			"faces": {
				"north": {"uv": [7.375, 2.25, 7.5, 2.5], "texture": "#0"},
				"east": {"uv": [7.375, 1.5, 7.875, 1.75], "texture": "#0"},
				"south": {"uv": [7.375, 2, 7.5, 2.25], "texture": "#0"},
				"west": {"uv": [7.375, 1.75, 7.875, 2], "texture": "#0"},
				"up": {"uv": [7.75, 1.5, 7.25, 1.375], "rotation": 90, "texture": "#0"},
				"down": {"uv": [8.25, 1.375, 7.75, 1.5], "rotation": 270, "texture": "#0"}
			}
		}
	],
	"display": {
		"thirdperson_righthand": {
			"rotation": [10, -172, -6],
			"translation": [-0.25, 3, 2.25]
		},
		"thirdperson_lefthand": {
			"rotation": [10, -172, -6],
			"translation": [-0.25, 3, 2.25]
		},
		"firstperson_righthand": {
			"rotation": [-10, 1, 0],
			"translation": [1.75, -1, 0],
			"scale": [0.85, 0.85, 0.85]
		},
		"firstperson_lefthand": {
			"rotation": [-10, 1, 0],
			"translation": [1.75, -1, 0],
			"scale": [0.85, 0.85, 0.85]
		},
		"ground": {
			"rotation": [-90, -90, 0],
			"translation": [0, -1, 1.75],
			"scale": [0.25, 0.25, 0.25]
		},
		"gui": {
			"rotation": [36, 33, -57],
			"translation": [-3.75, -3.5, 0],
			"scale": [0.75, 0.75, 0.75]
		},
		"fixed": {
			"rotation": [0, -90, 0],
			"translation": [0, -4.5, 0],
			"scale": [1.25, 1.25, 1.25]
		}
	}
}