{
	"credit": "Made with Blockbench",
	"textures": {
		"0": "./pavuk1",
		"particle": "./pavuk1"
	},
	"elements": [
		{
			"from": [7, 0, 6.5],
			"to": [9, 3, 9.5],
			"rotation": {"angle": 0, "axis": "y", "origin": [7, 0, 3.5]},
			"faces": {
				"north": {"uv": [9, 3, 11, 6], "texture": "#0"},
				"east": {"uv": [7, 6, 10, 9], "texture": "#0"},
				"south": {"uv": [7, 9, 9, 12], "texture": "#0"},
				"west": {"uv": [9, 0, 12, 3], "texture": "#0"},
				"up": {"uv": [11, 12, 9, 9], "texture": "#0"},
				"down": {"uv": [12, 6, 10, 9], "texture": "#0"}
			}
		},
		{
			"from": [8, -2, 3.5],
			"to": [8, 4, 6.5],
			"rotation": {"angle": 0, "axis": "y", "origin": [7, -3, 4.5]},
			"faces": {
				"north": {"uv": [0, 0, 0, 6], "texture": "#0"},
				"east": {"uv": [6, 0, 9, 6], "texture": "#0"},
				"south": {"uv": [0, 0, 0, 6], "texture": "#0"},
				"west": {"uv": [9, 0, 6, 6], "texture": "#0"},
				"up": {"uv": [0, 3, 0, 0], "texture": "#0"},
				"down": {"uv": [0, 0, 0, 3], "texture": "#0"}
			}
		},
		{
			"from": [8, -2, 9.5],
			"to": [8, 4, 12.5],
			"rotation": {"angle": 0, "axis": "y", "origin": [7, -3, 4.5]},
			"faces": {
				"north": {"uv": [0, 0, 0, 6], "texture": "#0"},
				"east": {"uv": [9, 0, 6, 6], "texture": "#0"},
				"south": {"uv": [0, 0, 0, 6], "texture": "#0"},
				"west": {"uv": [6, 0, 9, 6], "texture": "#0"},
				"up": {"uv": [0, 3, 0, 0], "texture": "#0"},
				"down": {"uv": [0, 0, 0, 3], "texture": "#0"}
			}
		},
		{
			"from": [8, 3, 7],
			"to": [8, 10, 9],
			"rotation": {"angle": 0, "axis": "y", "origin": [8, 0, 7]},
			"faces": {
				"north": {"uv": [0, 0, 0, 7], "texture": "#0"},
				"east": {"uv": [5, 6, 7, 13], "texture": "#0"},
				"south": {"uv": [0, 0, 0, 7], "texture": "#0"},
				"west": {"uv": [5, 6, 7, 13], "texture": "#0"},
				"up": {"uv": [0, 2, 0, 0], "texture": "#0"},
				"down": {"uv": [0, 0, 0, 2], "texture": "#0"}
			}
		},
		{
			"from": [6.875, -0.125, 6.375],
			"to": [6.875, 2.125, 9.625],
			"rotation": {"angle": 0, "axis": "y", "origin": [13.75, -0.25, 12.75]},
			"faces": {
				"north": {"uv": [3, 6.25, 3, 9.25], "texture": "#0"},
				"east": {"uv": [1.5, 1, 4.5, 3], "texture": "#0"},
				"south": {"uv": [6, 6.25, 6, 9.25], "texture": "#0"},
				"west": {"uv": [1.5, 1, 4.5, 3], "texture": "#0"},
				"up": {"uv": [3, 6.25, 3, 3.25], "texture": "#0"},
				"down": {"uv": [3, 3.25, 3, 6.25], "texture": "#0"}
			}
		}
	],
	"display": {
		"thirdperson_righthand": {
			"rotation": [68, 180, 0],
			"translation": [0, -3, -2]
		},
		"thirdperson_lefthand": {
			"rotation": [68, 0, 0],
			"translation": [0, -3, -2]
		},
		"firstperson_righthand": {
			"rotation": [0, 27, 0],
			"translation": [0.5, 7.5, 0.25],
			"scale": [0.75, 0.75, 0.75]
		},
		"firstperson_lefthand": {
			"rotation": [0, -162, 0],
			"translation": [0.5, 7.5, 0.25],
			"scale": [0.75, 0.75, 0.75]
		},
		"ground": {
			"rotation": [-90, 90, 0],
			"translation": [0, 0, -3],
			"scale": [0.5, 0.5, 0.5]
		},
		"gui": {
			"rotation": [53, 45, -29],
			"translation": [2.75, 4.75, 0],
			"scale": [1.25, 1.25, 1.25]
		},
		"fixed": {
			"rotation": [90, 0, 0],
			"translation": [0, 0, -3],
			"scale": [2, 2, 2]
		}
	}
}