{
	"credit": "Made with Blockbench",
	"texture_size": [32, 32],
	"textures": {
		"0": "mantis_blade",
		"particle": "mantis_blade"
	},
	"elements": [
		{
			"from": [6, 2, 6],
			"to": [10, 8, 10],
			"faces": {
				"north": {"uv": [4, 0, 6, 3], "texture": "#0"},
				"east": {"uv": [4, 3, 6, 6], "texture": "#0"},
				"south": {"uv": [6, 0, 8, 3], "texture": "#0"},
				"west": {"uv": [6, 3, 8, 6], "texture": "#0"},
				"up": {"uv": [6, 8, 4, 6], "texture": "#0"},
				"down": {"uv": [8, 6, 6, 8], "texture": "#0"}
			}
		},
		{
			"from": [9, 3, 7],
			"to": [11, 10, 9],
			"rotation": {"angle": -22.5, "axis": "z", "origin": [11, 6.5, 8]},
			"faces": {
				"north": {"uv": [4, 8, 5, 11.5], "texture": "#0"},
				"east": {"uv": [8, 4, 9, 7.5], "texture": "#0"},
				"south": {"uv": [5, 8, 6, 11.5], "texture": "#0"},
				"west": {"uv": [6, 8, 7, 11.5], "texture": "#0"},
				"up": {"uv": [1, 9.5, 0, 8.5], "texture": "#0"},
				"down": {"uv": [2, 8.5, 1, 9.5], "texture": "#0"}
			}
		},
		{
			"from": [11, 7.5, 7.49],
			"to": [13, 9.5, 8.51],
			"rotation": {"angle": 45, "axis": "z", "origin": [12, 9, 8]},
			"faces": {
				"north": {"uv": [2, 8.5, 3, 9.5], "texture": "#0"},
				"east": {"uv": [9.5, 5.5, 10, 6.5], "texture": "#0"},
				"south": {"uv": [3, 8.5, 4, 9.5], "texture": "#0"},
				"west": {"uv": [9.5, 6.5, 10, 7.5], "texture": "#0"},
				"up": {"uv": [10.5, 8, 9.5, 7.5], "texture": "#0"},
				"down": {"uv": [9, 9.5, 8, 10], "texture": "#0"}
			}
		},
		{
			"from": [11.75, 4.5, 7.5],
			"to": [13.75, 8.5, 8.5],
			"faces": {
				"north": {"uv": [7, 8, 8, 10], "texture": "#0"},
				"east": {"uv": [9, 4, 9.5, 6], "texture": "#0"},
				"south": {"uv": [8, 7.5, 9, 9.5], "texture": "#0"},
				"west": {"uv": [9, 6, 9.5, 8], "texture": "#0"},
				"up": {"uv": [10, 10, 9, 9.5], "texture": "#0"},
				"down": {"uv": [1, 10, 0, 10.5], "texture": "#0"}
			}
		},
		{
			"from": [11, -6, 8],
			"to": [15, 7, 8],
			"rotation": {"angle": 0, "axis": "z", "origin": [13, 0.5, 8]},
			"faces": {
				"north": {"uv": [0, 0, 2, 6.5], "texture": "#0"},
				"east": {"uv": [0, 0, 0, 6.5], "texture": "#0"},
				"south": {"uv": [2, 0, 4, 6.5], "texture": "#0"},
				"west": {"uv": [0, 0, 0, 6.5], "texture": "#0"},
				"up": {"uv": [2, 0, 0, 0], "texture": "#0"},
				"down": {"uv": [2, 0, 0, 0], "texture": "#0"}
			}
		},
		{
			"from": [5.9, 1.9, 5.9],
			"to": [10.1, 3.1, 10.1],
			"faces": {
				"north": {"uv": [9, 8, 11, 8.5], "texture": "#0"},
				"east": {"uv": [9, 8.5, 11, 9], "texture": "#0"},
				"south": {"uv": [9, 9, 11, 9.5], "texture": "#0"},
				"west": {"uv": [0, 9.5, 2, 10], "texture": "#0"},
				"up": {"uv": [2, 8.5, 0, 6.5], "texture": "#0"},
				"down": {"uv": [4, 6.5, 2, 8.5], "texture": "#0"}
			}
		},
		{
			"from": [5.9, 6.9, 5.9],
			"to": [10.1, 8.1, 10.1],
			"faces": {
				"north": {"uv": [2, 9.5, 4, 10], "texture": "#0"},
				"east": {"uv": [9.5, 4, 11.5, 4.5], "texture": "#0"},
				"south": {"uv": [9.5, 4.5, 11.5, 5], "texture": "#0"},
				"west": {"uv": [9.5, 5, 11.5, 5.5], "texture": "#0"},
				"up": {"uv": [10, 2, 8, 0], "texture": "#0"},
				"down": {"uv": [10, 2, 8, 4], "texture": "#0"}
			}
		}
	],
	"display": {
		"thirdperson_righthand": {
			"rotation": [90, 0, 0],
			"translation": [0, -2, 8],
			"scale": [1.01, 1.01, 1.01]
		},
		"thirdperson_lefthand": {
			"rotation": [90, 180, 0],
			"translation": [0, -2, 8],
			"scale": [1.01, 1.01, 1.01]
		},
		"firstperson_righthand": {
			"rotation": [110, 60, 0],
			"translation": [0, -2, 0]
		},
		"firstperson_lefthand": {
			"rotation": [110, -120, 0],
			"translation": [0, -2, 0]
		},
		"ground": {
			"rotation": [127, 21, 0]
		},
		"gui": {
			"rotation": [0, 26, 140],
			"translation": [-1, -5, 0]
		},
		"fixed": {
			"rotation": [0, 90, 0],
			"translation": [0, 7.5, -3],
			"scale": [2, 2, 2]
		}
	}
}