{"credit": "Made by Mr_San1X", "texture_size": [96, 96], "textures": {"1": "./lincoln", "particle": "./lincoln"}, "elements": [{"from": [0, 2.5, -14.5], "to": [1, 7.5, -12.5], "rotation": {"angle": 0, "axis": "y", "origin": [8.5, 0, 8.5]}, "faces": {"north": {"uv": [5.16667, 11.66667, 5.33333, 12.5], "texture": "#1"}, "east": {"uv": [11.83333, 10.33333, 12.16667, 11.16667], "texture": "#1"}, "south": {"uv": [2.5, 11.83333, 2.66667, 12.66667], "texture": "#1"}, "west": {"uv": [11, 11.83333, 11.33333, 12.66667], "texture": "#1"}, "up": {"uv": [4.33333, 9.66667, 4.16667, 9.33333], "texture": "#1"}, "down": {"uv": [2.83333, 11, 2.66667, 11.33333], "texture": "#1"}}}, {"from": [6, 2.5, -14.5], "to": [11, 7.5, -12.5], "rotation": {"angle": 0, "axis": "y", "origin": [8.5, 0, 8.5]}, "faces": {"north": {"uv": [1, 11, 1.83333, 11.83333], "texture": "#1"}, "east": {"uv": [11.33333, 11.83333, 11.66667, 12.66667], "texture": "#1"}, "south": {"uv": [1.83333, 11, 2.66667, 11.83333], "texture": "#1"}, "west": {"uv": [0, 12, 0.33333, 12.83333], "texture": "#1"}, "up": {"uv": [11.66667, 9.5, 10.83333, 9.16667], "texture": "#1"}, "down": {"uv": [12.5, 9.16667, 11.66667, 9.5], "texture": "#1"}}}, {"from": [7.5, 7.5, -14], "to": [9.5, 9.5, -14], "rotation": {"angle": 0, "axis": "y", "origin": [8.5, 0, 8.5]}, "faces": {"north": {"uv": [3.83333, 9.33333, 4.16667, 9.66667], "texture": "#1"}, "east": {"uv": [0, 0, 0, 0.33333], "texture": "#1"}, "south": {"uv": [8.5, 12, 8.83333, 12.33333], "texture": "#1"}, "west": {"uv": [0, 0, 0, 0.33333], "texture": "#1"}, "up": {"uv": [0.33333, 0, 0, 0], "texture": "#1"}, "down": {"uv": [0.33333, 0, 0, 0], "texture": "#1"}}}, {"from": [16, 2.5, -14.5], "to": [17, 7.5, -12.5], "rotation": {"angle": 0, "axis": "y", "origin": [8.5, 0, 8.5]}, "faces": {"north": {"uv": [8.16667, 12, 8.33333, 12.83333], "texture": "#1"}, "east": {"uv": [0.33333, 12, 0.66667, 12.83333], "texture": "#1"}, "south": {"uv": [8.33333, 12, 8.5, 12.83333], "texture": "#1"}, "west": {"uv": [0.66667, 12, 1, 12.83333], "texture": "#1"}, "up": {"uv": [3.83333, 11.66667, 3.66667, 11.33333], "texture": "#1"}, "down": {"uv": [9, 12, 8.83333, 12.33333], "texture": "#1"}}}, {"from": [0, 2.5, -12.5], "to": [17, 7.5, 25.5], "rotation": {"angle": 0, "axis": "y", "origin": [8.5, 0, 8.5]}, "faces": {"north": {"uv": [0, 9.33333, 2.83333, 10.16667], "texture": "#1"}, "east": {"uv": [8.16667, 0, 14.5, 0.83333], "texture": "#1"}, "south": {"uv": [0, 10.16667, 2.83333, 11], "texture": "#1"}, "west": {"uv": [8.16667, 0.83333, 14.5, 1.66667], "texture": "#1"}, "up": {"uv": [8.16667, 6.33333, 5.33333, 0], "texture": "#1"}, "down": {"uv": [8.16667, 6.33333, 5.33333, 12.66667], "texture": "#1"}}}, {"from": [0, 2.5, 25.5], "to": [17, 7.5, 30.5], "rotation": {"angle": 0, "axis": "y", "origin": [8.5, 0, 8.5]}, "faces": {"north": {"uv": [8.16667, 10.33333, 11, 11.16667], "texture": "#1"}, "east": {"uv": [11, 10.33333, 11.83333, 11.16667], "texture": "#1"}, "south": {"uv": [10.83333, 5, 13.66667, 5.83333], "texture": "#1"}, "west": {"uv": [8.16667, 11.16667, 9, 12], "texture": "#1"}, "up": {"uv": [13.66667, 6.66667, 10.83333, 5.83333], "texture": "#1"}, "down": {"uv": [13.66667, 6.66667, 10.83333, 7.5], "texture": "#1"}}}, {"from": [0.5, -0.5, -2.5], "to": [16.5, 6, -2.5], "rotation": {"angle": 45, "axis": "x", "origin": [8.5, 0, 8.5]}, "faces": {"north": {"uv": [8.16667, 5, 10.83333, 6.08333], "texture": "#1"}, "east": {"uv": [0, 0, 0, 1.08333], "texture": "#1"}, "south": {"uv": [8.16667, 6.16667, 10.83333, 7.25], "texture": "#1"}, "west": {"uv": [0, 0, 0, 1.08333], "texture": "#1"}, "up": {"uv": [2.66667, 0, 0, 0], "texture": "#1"}, "down": {"uv": [2.66667, 0, 0, 0], "texture": "#1"}}}, {"from": [0.5, -3.35, 21.25], "to": [16.5, 3.25, 21.25], "rotation": {"angle": -45, "axis": "x", "origin": [8.5, 0, 7.5]}, "faces": {"north": {"uv": [8.16667, 7.33333, 10.83333, 8.41667], "texture": "#1"}, "east": {"uv": [0, 0, 0, 1.08333], "texture": "#1"}, "south": {"uv": [8.16667, 8.5, 10.83333, 9.58333], "texture": "#1"}, "west": {"uv": [0, 0, 0, 1.08333], "texture": "#1"}, "up": {"uv": [2.66667, 0, 0, 0], "texture": "#1"}, "down": {"uv": [2.66667, 0, 0, 0], "texture": "#1"}}}, {"from": [2.25, 12.01981, 4.96447], "to": [14.75, 12.01981, 14.96447], "rotation": {"angle": 0, "axis": "y", "origin": [6.75, 0.01981, 8.46447]}, "faces": {"north": {"uv": [0, 0, 2.08333, 0], "texture": "#1"}, "east": {"uv": [0, 0, 1.66667, 0], "texture": "#1"}, "south": {"uv": [0, 0, 2.08333, 0], "texture": "#1"}, "west": {"uv": [0, 0, 1.66667, 0], "texture": "#1"}, "up": {"uv": [2.08333, 9.33333, 0, 7.66667], "texture": "#1"}, "down": {"uv": [4.25, 7.66667, 2.16667, 9.33333], "texture": "#1"}}}, {"from": [0.5, 0.5, -15.5], "to": [16.5, 2.5, 30.5], "rotation": {"angle": 0, "axis": "y", "origin": [8.5, 0, 8.5]}, "faces": {"north": {"uv": [10.83333, 7.5, 13.5, 7.83333], "texture": "#1"}, "east": {"uv": [8.16667, 9.66667, 15.83333, 10], "texture": "#1"}, "south": {"uv": [10.83333, 7.83333, 13.5, 8.16667], "texture": "#1"}, "west": {"uv": [8.16667, 10, 15.83333, 10.33333], "texture": "#1"}, "up": {"uv": [2.66667, 7.66667, 0, 0], "texture": "#1"}, "down": {"uv": [5.33333, 0, 2.66667, 7.66667], "texture": "#1"}}}, {"from": [0.25, -0.75, -10.5], "to": [2.75, 4.75, -5], "rotation": {"angle": 0, "axis": "y", "origin": [8.5, 0, 8.5]}, "faces": {"north": {"uv": [4.83333, 9.66667, 5.25, 10.58333], "texture": "#1"}, "east": {"uv": [4.33333, 7.66667, 5.25, 8.58333], "texture": "#1"}, "south": {"uv": [4.83333, 10.66667, 5.25, 11.58333], "texture": "#1"}, "west": {"uv": [4.33333, 8.66667, 5.25, 9.58333], "texture": "#1"}, "up": {"uv": [3.08333, 12.25, 2.66667, 11.33333], "texture": "#1"}, "down": {"uv": [3.58333, 11.33333, 3.16667, 12.25], "texture": "#1"}}}, {"from": [14.25, -0.75, -10.5], "to": [16.75, 4.75, -5], "rotation": {"angle": 0, "axis": "y", "origin": [8.5, 0, 8.5]}, "faces": {"north": {"uv": [3.66667, 11.66667, 4.08333, 12.58333], "texture": "#1"}, "east": {"uv": [2.83333, 9.33333, 3.75, 10.25], "texture": "#1"}, "south": {"uv": [4.16667, 11.66667, 4.58333, 12.58333], "texture": "#1"}, "west": {"uv": [3.83333, 9.66667, 4.75, 10.58333], "texture": "#1"}, "up": {"uv": [5.08333, 12.58333, 4.66667, 11.66667], "texture": "#1"}, "down": {"uv": [12.08333, 11.16667, 11.66667, 12.08333], "texture": "#1"}}}, {"from": [0.25, -0.75, 17], "to": [2.75, 4.75, 22.5], "rotation": {"angle": 0, "axis": "y", "origin": [8.5, 0, 8.5]}, "faces": {"north": {"uv": [1, 11.83333, 1.41667, 12.75], "texture": "#1"}, "east": {"uv": [2.83333, 10.33333, 3.75, 11.25], "texture": "#1"}, "south": {"uv": [1.5, 11.83333, 1.91667, 12.75], "texture": "#1"}, "west": {"uv": [3.83333, 10.66667, 4.75, 11.58333], "texture": "#1"}, "up": {"uv": [2.41667, 12.75, 2, 11.83333], "texture": "#1"}, "down": {"uv": [12.25, 8.16667, 11.83333, 9.08333], "texture": "#1"}}}, {"from": [14.25, -0.75, 17], "to": [16.75, 4.75, 22.5], "rotation": {"angle": 0, "axis": "y", "origin": [8.5, 0, 8.5]}, "faces": {"north": {"uv": [9, 11.83333, 9.41667, 12.75], "texture": "#1"}, "east": {"uv": [10.83333, 8.16667, 11.75, 9.08333], "texture": "#1"}, "south": {"uv": [9.5, 11.83333, 9.91667, 12.75], "texture": "#1"}, "west": {"uv": [0, 11, 0.91667, 11.91667], "texture": "#1"}, "up": {"uv": [10.41667, 12.75, 10, 11.83333], "texture": "#1"}, "down": {"uv": [10.91667, 11.83333, 10.5, 12.75], "texture": "#1"}}}, {"from": [-1.75, 3.75, 0], "to": [-1.75, 8.75, 25], "rotation": {"angle": -22.5, "axis": "z", "origin": [8.5, 0, 8.5]}, "faces": {"north": {"uv": [0, 0, 0, 0.83333], "texture": "#1"}, "east": {"uv": [8.16667, 1.66667, 12.33333, 2.5], "texture": "#1"}, "south": {"uv": [0, 0, 0, 0.83333], "texture": "#1"}, "west": {"uv": [8.16667, 2.5, 12.33333, 3.33333], "texture": "#1"}, "up": {"uv": [0, 4.16667, 0, 0], "texture": "#1"}, "down": {"uv": [0, 0, 0, 4.16667], "texture": "#1"}}}, {"from": [18.75, 3.35, 0], "to": [18.75, 8.35, 25], "rotation": {"angle": 22.5, "axis": "z", "origin": [7.5, 0, 8.5]}, "faces": {"north": {"uv": [0, 0, 0, 0.83333], "texture": "#1"}, "east": {"uv": [8.16667, 3.33333, 12.33333, 4.16667], "texture": "#1"}, "south": {"uv": [0, 0, 0, 0.83333], "texture": "#1"}, "west": {"uv": [8.16667, 4.16667, 12.33333, 5], "texture": "#1"}, "up": {"uv": [0, 4.16667, 0, 0], "texture": "#1"}, "down": {"uv": [0, 0, 0, 4.16667], "texture": "#1"}}}, {"from": [-3, 7, 3], "to": [1, 11, 3], "faces": {"north": {"uv": [9, 11.16667, 9.66667, 11.83333], "texture": "#1"}, "east": {"uv": [0, 0, 0, 0.66667], "texture": "#1"}, "south": {"uv": [9.66667, 11.16667, 10.33333, 11.83333], "texture": "#1"}, "west": {"uv": [0, 0, 0, 0.66667], "texture": "#1"}, "up": {"uv": [0.66667, 0, 0, 0], "texture": "#1"}, "down": {"uv": [0.66667, 0, 0, 0], "texture": "#1"}}}, {"from": [16, 7, 3], "to": [20, 11, 3], "faces": {"north": {"uv": [10.33333, 11.16667, 11, 11.83333], "texture": "#1"}, "east": {"uv": [0, 0, 0, 0.66667], "texture": "#1"}, "south": {"uv": [11, 11.16667, 11.66667, 11.83333], "texture": "#1"}, "west": {"uv": [0, 0, 0, 0.66667], "texture": "#1"}, "up": {"uv": [0.66667, 0, 0, 0], "texture": "#1"}, "down": {"uv": [0.66667, 0, 0, 0], "texture": "#1"}}}, {"from": [3, 0.5, -11], "to": [0, 5, -4.5], "rotation": {"angle": 0, "axis": "y", "origin": [16, 0, 0]}, "faces": {"north": {"uv": [16, 15.25, 15.5, 16], "texture": "#1"}, "east": {"uv": [15.5, 15.25, 14.41667, 16], "texture": "#1"}, "south": {"uv": [16, 13.41667, 15.5, 14.16667], "texture": "#1"}, "west": {"uv": [14.41667, 15.25, 13.33333, 16], "texture": "#1"}, "up": {"uv": [15.5, 14.16667, 15, 15.25], "texture": "#1"}, "down": {"uv": [16, 14.16667, 15.5, 15.25], "texture": "#1"}}}, {"from": [17, 0.5, -11], "to": [14, 5, -4.5], "faces": {"north": {"uv": [15.5, 15.25, 16, 16], "texture": "#1"}, "east": {"uv": [13.33333, 15.25, 14.41667, 16], "texture": "#1"}, "south": {"uv": [15.5, 13.41667, 16, 14.16667], "texture": "#1"}, "west": {"uv": [14.41667, 15.25, 15.5, 16], "texture": "#1"}, "up": {"uv": [15, 14.16667, 15.5, 15.25], "texture": "#1"}, "down": {"uv": [15.5, 14.16667, 16, 15.25], "texture": "#1"}}}, {"from": [3, 0.5, 16.5], "to": [0, 5, 23], "rotation": {"angle": 0, "axis": "y", "origin": [16, 0, 0]}, "faces": {"north": {"uv": [16, 15.25, 15.5, 16], "texture": "#1"}, "east": {"uv": [15.5, 15.25, 14.41667, 16], "texture": "#1"}, "south": {"uv": [16, 13.41667, 15.5, 14.16667], "texture": "#1"}, "west": {"uv": [14.41667, 15.25, 13.33333, 16], "texture": "#1"}, "up": {"uv": [15.5, 14.16667, 15, 15.25], "texture": "#1"}, "down": {"uv": [16, 14.16667, 15.5, 15.25], "texture": "#1"}}}, {"from": [17, 0.5, 16.5], "to": [14, 5, 23], "faces": {"north": {"uv": [15.5, 15.25, 16, 16], "texture": "#1"}, "east": {"uv": [13.33333, 15.25, 14.41667, 16], "texture": "#1"}, "south": {"uv": [15.5, 13.41667, 16, 14.16667], "texture": "#1"}, "west": {"uv": [14.41667, 15.25, 15.5, 16], "texture": "#1"}, "up": {"uv": [15, 14.16667, 15.5, 15.25], "texture": "#1"}, "down": {"uv": [15.5, 14.16667, 16, 15.25], "texture": "#1"}}}], "display": {"thirdperson_righthand": {"rotation": [-6, 49, 0], "translation": [-1, 1, -0.5], "scale": [0.2, 0.2, 0.2]}, "thirdperson_lefthand": {"rotation": [54.25, 0, 0], "translation": [-13, -1.25, 13.5], "scale": [2.2, 2.2, 2.2]}, "firstperson_righthand": {"rotation": [0, 116, 0], "translation": [1, 4.25, -0.5], "scale": [0.3, 0.3, 0.3]}, "firstperson_lefthand": {"translation": [1, 4.75, -0.5], "scale": [0, 0, 0]}, "ground": {"translation": [0, 3, 0], "scale": [0.25, 0.25, 0.25]}, "gui": {"rotation": [31, -148, 0], "translation": [0.25, 1, 0], "scale": [0.7, 0.7, 0.7]}, "head": {"translation": [12.75, -3.5, 1.25], "scale": [3.5, 3.5, 3.5]}, "fixed": {"rotation": [-90, 0, 0], "translation": [-1.75, -2, -34.25], "scale": [4, 4, 4]}}, "groups": [{"name": "bone", "origin": [0, 0, 0], "color": 0, "nbt": "{}", "children": [{"name": "group", "origin": [8.5, 0, 8.5], "color": 0, "nbt": "{}", "children": [0, 1, 2, 3, 4, 5, 6, 7, 8, 9, 10, 11, 12, 13, 14, 15]}, 16, 17]}, 18, 19, 20, 21]}