{
	"credit": "Made with Blockbench",
	"texture_size": [32, 32],
	"textures": {
		"0": "./crystallcabuto",
		"particle": "./crystallcabuto"
	},
	"elements": [
		{
			"from": [4, 11, 4],
			"to": [12, 16, 12],
			"rotation": {"angle": 0, "axis": "y", "origin": [0, 11, 0]},
			"faces": {
				"north": {"uv": [4, 0, 8, 2.5], "texture": "#0"},
				"east": {"uv": [4, 2.5, 8, 5], "texture": "#0"},
				"south": {"uv": [4, 5, 8, 7.5], "texture": "#0"},
				"west": {"uv": [4, 7.5, 8, 10], "texture": "#0"},
				"up": {"uv": [4, 4, 0, 0], "texture": "#0"},
				"down": {"uv": [4, 4, 0, 8], "texture": "#0"}
			}
		},
		{
			"from": [4.1, 10.5, 1.5],
			"to": [11.9, 11.5, 5.5],
			"rotation": {"angle": -22.5, "axis": "x", "origin": [8, 11.5, 2]},
			"faces": {
				"north": {"uv": [8, 2, 12, 2.5], "texture": "#0"},
				"east": {"uv": [8, 3, 10, 3.5], "texture": "#0"},
				"south": {"uv": [8, 2.5, 12, 3], "texture": "#0"},
				"west": {"uv": [8, 3.5, 10, 4], "texture": "#0"},
				"up": {"uv": [4, 10, 0, 8], "texture": "#0"},
				"down": {"uv": [0, 8, 4, 10], "texture": "#0"}
			}
		},
		{
			"from": [4, 8.25, 11.25],
			"to": [12, 12.25, 12.25],
			"rotation": {"angle": -22.5, "axis": "x", "origin": [8, 11.5, 14]},
			"faces": {
				"north": {"uv": [4, 10, 0, 8], "rotation": 180, "texture": "#0"},
				"east": {"uv": [8, 3, 10, 3.5], "rotation": 90, "texture": "#0"},
				"south": {"uv": [4, 8, 0, 10], "texture": "#0"},
				"west": {"uv": [8, 3.5, 10, 4], "rotation": 270, "texture": "#0"},
				"up": {"uv": [8, 2.5, 12, 3], "texture": "#0"},
				"down": {"uv": [8, 2, 12, 2.5], "rotation": 180, "texture": "#0"}
			}
		},
		{
			"from": [2.25, 13.25, 3.75],
			"to": [7.25, 20.25, 3.75],
			"rotation": {"angle": 22.5, "axis": "z", "origin": [6.5, 16.25, 3.75]},
			"faces": {
				"north": {"uv": [2.5, 10.5, 0, 14], "texture": "#0"},
				"east": {"uv": [0, 0, 0, 3], "texture": "#0"},
				"south": {"uv": [0, 10.5, 2.5, 14], "texture": "#0"},
				"west": {"uv": [0, 0, 0, 3], "texture": "#0"},
				"up": {"uv": [2, 0, 0, 0], "texture": "#0"},
				"down": {"uv": [2, 0, 0, 0], "texture": "#0"}
			}
		},
		{
			"from": [8.75, 13.25, 3.75],
			"to": [13.75, 20.25, 3.75],
			"rotation": {"angle": -22.5, "axis": "z", "origin": [9.5, 16.25, 3.75]},
			"faces": {
				"north": {"uv": [0, 10.5, 2.5, 14], "texture": "#0"},
				"east": {"uv": [0, 0, 0, 3], "texture": "#0"},
				"south": {"uv": [2.5, 10.5, 0, 14], "texture": "#0"},
				"west": {"uv": [0, 0, 0, 3], "texture": "#0"},
				"up": {"uv": [2, 0, 0, 0], "rotation": 180, "texture": "#0"},
				"down": {"uv": [2, 0, 0, 0], "rotation": 180, "texture": "#0"}
			}
		},
		{
			"from": [3.56066, 6.93934, 4],
			"to": [4.56066, 11.93934, 12],
			"rotation": {"angle": -22.5, "axis": "z", "origin": [2.56066, 10.43934, 8]},
			"faces": {
				"north": {"uv": [10, 3.5, 12.5, 4], "rotation": 90, "texture": "#0"},
				"east": {"uv": [10.5, 8, 8, 12], "rotation": 270, "texture": "#0"},
				"south": {"uv": [4, 10, 6.5, 10.5], "rotation": 270, "texture": "#0"},
				"west": {"uv": [10.5, 8, 8, 4], "rotation": 270, "texture": "#0"},
				"up": {"uv": [0, 10, 4, 10.5], "rotation": 270, "texture": "#0"},
				"down": {"uv": [10, 3, 14, 3.5], "rotation": 270, "texture": "#0"}
			}
		},
		{
			"from": [11.43934, 6.93934, 4],
			"to": [12.43934, 11.93934, 12],
			"rotation": {"angle": 22.5, "axis": "z", "origin": [13.43934, 10.43934, 8]},
			"faces": {
				"north": {"uv": [10, 3.5, 12.5, 4], "rotation": 90, "texture": "#0"},
				"east": {"uv": [10.5, 8, 8, 12], "rotation": 270, "texture": "#0"},
				"south": {"uv": [4, 10, 6.5, 10.5], "rotation": 270, "texture": "#0"},
				"west": {"uv": [10.5, 8, 8, 4], "rotation": 270, "texture": "#0"},
				"up": {"uv": [0, 10, 4, 10.5], "rotation": 270, "texture": "#0"},
				"down": {"uv": [10, 3, 14, 3.5], "rotation": 270, "texture": "#0"}
			}
		},
		{
			"from": [7, 12.75, 3.5],
			"to": [9, 14.75, 3.5],
			"rotation": {"angle": 0, "axis": "y", "origin": [0, 10.25, 0]},
			"faces": {
				"north": {"uv": [6.5, 10, 7.5, 11], "texture": "#0"},
				"east": {"uv": [0, 0, 0, 1], "texture": "#0"},
				"south": {"uv": [6.5, 11, 7.5, 10], "texture": "#0"},
				"west": {"uv": [0, 0, 0, 1], "texture": "#0"},
				"up": {"uv": [1, 0, 0, 0], "texture": "#0"},
				"down": {"uv": [1, 0, 0, 0], "texture": "#0"}
			}
		},
		{
			"from": [0, 13, 8.5],
			"to": [5, 21, 8.5],
			"rotation": {"angle": 22.5, "axis": "y", "origin": [2.5, 15, 9]},
			"faces": {
				"north": {"uv": [10.5, 4, 13, 8], "texture": "#0"},
				"east": {"uv": [0, 0, 0, 4], "texture": "#0"},
				"south": {"uv": [13, 4, 10.5, 8], "texture": "#0"},
				"west": {"uv": [0, 0, 0, 4], "texture": "#0"},
				"up": {"uv": [2.5, 0, 0, 0], "rotation": 180, "texture": "#0"},
				"down": {"uv": [2.5, 0, 0, 0], "rotation": 180, "texture": "#0"}
			}
		},
		{
			"from": [12, 14, 8.5],
			"to": [15, 18, 8.5],
			"rotation": {"angle": 45, "axis": "y", "origin": [13.5, 16, 9.5]},
			"faces": {
				"north": {"uv": [6, 10.5, 4.5, 12.5], "texture": "#0"},
				"east": {"uv": [0, 0, 0, 2], "texture": "#0"},
				"south": {"uv": [4.5, 10.5, 6, 12.5], "texture": "#0"},
				"west": {"uv": [0, 0, 0, 2], "texture": "#0"},
				"up": {"uv": [2, 0, 0, 0], "texture": "#0"},
				"down": {"uv": [2, 0, 0, 0], "texture": "#0"}
			}
		}
	],
	"display": {
		"thirdperson_righthand": {
			"rotation": [-33, 7, -9],
			"translation": [-0.5, -4, -3.75]
		},
		"thirdperson_lefthand": {
			"rotation": [-33, 7, -9],
			"translation": [-0.5, -4, -3.75]
		},
		"firstperson_righthand": {
			"rotation": [-20, 0, 0],
			"translation": [0, -3, 0]
		},
		"firstperson_lefthand": {
			"rotation": [-20, 0, 0],
			"translation": [0, -3, 0]
		},
		"gui": {
			"rotation": [45, -145, 0],
			"translation": [0, -2.5, 0]
		},
		"head": {
			"translation": [0, -4.25, 0],
			"scale": [1.9, 1.9, 1.9]
		},
		"fixed": {
			"rotation": [-90, 0, 0],
			"translation": [0, 0, -2.75],
			"scale": [2, 2, 2]
		}
	}
}